chandra_parser/__init__.py
chandra_parser/cli.py
chandra_parser/client.py
chandra_parser/filter.py
chandra_parser-0.1.0.dist-info/METADATA
chandra_parser-0.1.0.dist-info/WHEEL
chandra_parser-0.1.0.dist-info/entry_points.txt
chandra_parser-0.1.0.dist-info/licenses/LICENSE
chandra_parser-0.1.0.dist-info/RECORD
