Metadata-Version: 2.4
Name: chandra-parser
Version: 0.1.0
Summary: PDF to Markdown parser using Datalab's Marker OCR API with optional GPT-based figure filtering
Project-URL: Homepage, https://github.com/adbutler007/chandra-parser
Project-URL: Documentation, https://github.com/adbutler007/chandra-parser#readme
Project-URL: Repository, https://github.com/adbutler007/chandra-parser
Project-URL: Issues, https://github.com/adbutler007/chandra-parser/issues
Author: Adam Butler
License: MIT
License-File: LICENSE
Keywords: datalab,document-processing,markdown,marker,ocr,pdf
Classifier: Development Status :: 4 - Beta
Classifier: Intended Audience :: Developers
Classifier: License :: OSI Approved :: MIT License
Classifier: Operating System :: OS Independent
Classifier: Programming Language :: Python :: 3
Classifier: Programming Language :: Python :: 3.11
Classifier: Programming Language :: Python :: 3.12
Classifier: Programming Language :: Python :: 3.13
Classifier: Topic :: Scientific/Engineering :: Image Recognition
Classifier: Topic :: Text Processing :: Markup :: Markdown
Requires-Python: >=3.11
Requires-Dist: click>=8.0
Requires-Dist: httpx>=0.25
Requires-Dist: openai>=1.0
Requires-Dist: pymupdf>=1.24
Provides-Extra: all
Requires-Dist: pytest-asyncio>=0.23; extra == 'all'
Requires-Dist: pytest>=8.0; extra == 'all'
Requires-Dist: ruff>=0.4; extra == 'all'
Provides-Extra: dev
Requires-Dist: pytest-asyncio>=0.23; extra == 'dev'
Requires-Dist: pytest>=8.0; extra == 'dev'
Requires-Dist: ruff>=0.4; extra == 'dev'
